MANIFEST.in
README.md
README.txt
setup.cfg
setup.py
colorview2d/__init__.py
colorview2d/cvfig.py
colorview2d/datafile.py
colorview2d/default.cv2d
colorview2d/fileloaders.py
colorview2d/imod.py
colorview2d/utils.py
colorview2d.egg-info/PKG-INFO
colorview2d.egg-info/SOURCES.txt
colorview2d.egg-info/dependency_links.txt
colorview2d.egg-info/requires.txt
colorview2d.egg-info/top_level.txt
test/__init__.py
test/cvfig_test.py
test/datafile_test.py
test/mods_test.py
test/test_tutorial.py