Metadata-Version: 1.1
Name: colorview2d
Version: 0.6.post4
Summary: 2d color plotting tool
Home-page: https://github.com/Loisel/colorview2d
Author: Alois Dirnaichner
Author-email: alo.dir@gmail.com
License: UNKNOWN
Download-URL: https://github.com/Loisel/colorview2d/tarball/v0.6
Keywords: plotting,colorplot,scientific,numpy,matplotlib
Platform: UNKNOWN
